bw25ui-0.46.1.dist-info/licenses/LICENSE
bw2ui/__init__.py
bw2ui/errors.py
bw2ui/notebook.py
bw2ui/bin/__init__.py
bw2ui/bin/bw2_browser.py
bw2ui/bin/bw2_web.py
bw2ui/web/__init__.py
bw2ui/web/jobs.py
bw2ui/web/utils.py
bw2ui/web/web_app.py
bw2ui/web/static/backgrid/backgrid-table.js
bw2ui/web/static/backgrid/backgrid.css
bw2ui/web/static/backgrid/backgrid.js
bw2ui/web/static/blueprint/ie.css
bw2ui/web/static/blueprint/print.css
bw2ui/web/static/blueprint/screen.css
bw2ui/web/static/blueprint/plugins/buttons/screen.css
bw2ui/web/static/css/base.css
bw2ui/web/static/css/hypertree.css
bw2ui/web/static/css/pure-bw2.css
bw2ui/web/static/d3-tip/d3-tip.css
bw2ui/web/static/d3-tip/d3-tip.js
bw2ui/web/static/img/favicon.ico
bw2ui/web/static/img/light_wool.png
bw2ui/web/static/img/linedpaper.png
bw2ui/web/static/img/llama.jpg
bw2ui/web/static/img/monster.jpg
bw2ui/web/static/jit/jit-yc.js
bw2ui/web/static/jit/jit.js
bw2ui/web/static/jqueryFileTree/jqueryFileTree.css
bw2ui/web/static/jqueryFileTree/jqueryFileTree.js
bw2ui/web/static/jqueryFileTree/images/application.png
bw2ui/web/static/jqueryFileTree/images/code.png
bw2ui/web/static/jqueryFileTree/images/css.png
bw2ui/web/static/jqueryFileTree/images/db.png
bw2ui/web/static/jqueryFileTree/images/directory.png
bw2ui/web/static/jqueryFileTree/images/doc.png
bw2ui/web/static/jqueryFileTree/images/file.png
bw2ui/web/static/jqueryFileTree/images/film.png
bw2ui/web/static/jqueryFileTree/images/flash.png
bw2ui/web/static/jqueryFileTree/images/folder_open.png
bw2ui/web/static/jqueryFileTree/images/html.png
bw2ui/web/static/jqueryFileTree/images/java.png
bw2ui/web/static/jqueryFileTree/images/linux.png
bw2ui/web/static/jqueryFileTree/images/music.png
bw2ui/web/static/jqueryFileTree/images/pdf.png
bw2ui/web/static/jqueryFileTree/images/php.png
bw2ui/web/static/jqueryFileTree/images/picture.png
bw2ui/web/static/jqueryFileTree/images/ppt.png
bw2ui/web/static/jqueryFileTree/images/psd.png
bw2ui/web/static/jqueryFileTree/images/ruby.png
bw25ui-0.46.1.dist-info/METADATA
bw25ui-0.46.1.dist-info/WHEEL
bw25ui-0.46.1.dist-info/entry_points.txt
bw25ui-0.46.1.dist-info/top_level.txt
bw25ui-0.46.1.dist-info/RECORD
