Metadata-Version: 2.4
Name: bw25ui
Version: 0.46.1
Summary: A web and command line user interface, part of the Brightway2 LCA framework https://brightway.dev.
Author-email: Chris Mutel <cmutel@gmail.com>
Maintainer-email: Tomás NAVARRETE GUTIÉRREZ <tngTUDOR@users.noreply.github.com>
Project-URL: source, https://github.com/brightway-lca/brightway2-ui
Project-URL: homepage, https://github.com/brightway-lca/brightway2-ui
Project-URL: tracker, https://github.com/brightway-lca/brightway2-ui/issues
Classifier: Development Status :: 4 - Beta
Classifier: Programming Language :: Python
Classifier: Programming Language :: Python :: 3
Classifier: Programming Language :: Python :: 3.9
Classifier: Programming Language :: Python :: 3.10
Classifier: Programming Language :: Python :: 3.11
Classifier: Programming Language :: Python :: 3.12
Classifier: Programming Language :: Python :: 3.13
Classifier: Natural Language :: English
Classifier: Operating System :: OS Independent
Classifier: Topic :: Scientific/Engineering
Requires-Python: >=3.9
License-File: LICENSE
Requires-Dist: bw2data
Requires-Dist: bw2calc
Requires-Dist: bw2analyzer
Requires-Dist: docopt
Requires-Dist: eight
Requires-Dist: flask
Requires-Dist: jinja2
Requires-Dist: stats_arrays
Requires-Dist: tabulate
Requires-Dist: genson
Requires-Dist: typing_extensions>=4.12.2; python_version >= "3.13"
Provides-Extra: testing
Requires-Dist: bw2ui; extra == "testing"
Requires-Dist: pytest; extra == "testing"
Requires-Dist: pytest-cov; extra == "testing"
Requires-Dist: python-coveralls; extra == "testing"
Provides-Extra: dev
Requires-Dist: build; extra == "dev"
Requires-Dist: pre-commit; extra == "dev"
Requires-Dist: black; extra == "dev"
Requires-Dist: isort; extra == "dev"
Requires-Dist: pylint; extra == "dev"
Requires-Dist: pytest; extra == "dev"
Requires-Dist: pytest-cov; extra == "dev"
Requires-Dist: pytest-randomly; extra == "dev"
Requires-Dist: setuptools; extra == "dev"
Provides-Extra: docs
Requires-Dist: furo==2025.9.25; extra == "docs"
Requires-Dist: myst_parser==4.0.1; extra == "docs"
Requires-Dist: sphinx==8.2.3; extra == "docs"
Dynamic: license-file
